delta_sharing/__init__.py
delta_sharing/_internal_auth.py
delta_sharing/_yarl_patch.py
delta_sharing/converter.py
delta_sharing/delta_sharing.py
delta_sharing/fake_checkpoint.py
delta_sharing/protocol.py
delta_sharing/reader.py
delta_sharing/rest_client.py
delta_sharing/version.py
delta_sharing-1.3.3.dist-info/licenses/NOTICE.txt
delta_sharing-1.3.3.dist-info/METADATA
delta_sharing-1.3.3.dist-info/WHEEL
delta_sharing-1.3.3.dist-info/top_level.txt
delta_sharing-1.3.3.dist-info/RECORD
